flowchem/__init__.py
flowchem/__main__.py
flowchem/py.typed
flowchem/client/__init__.py
flowchem/client/async_client.py
flowchem/client/client.py
flowchem/client/common.py
flowchem/client/component_client.py
flowchem/client/device_client.py
flowchem/components/__init__.py
flowchem/components/component_info.py
flowchem/components/device_info.py
flowchem/components/flowchem_component.py
flowchem/components/analytics/__init__.py
flowchem/components/analytics/dad.py
flowchem/components/analytics/hplc.py
flowchem/components/analytics/ir.py
flowchem/components/analytics/nmr.py
flowchem/components/pumps/__init__.py
flowchem/components/pumps/hplc_pump.py
flowchem/components/pumps/pump.py
flowchem/components/pumps/syringe_pump.py
flowchem/components/sensors/__init__.py
flowchem/components/sensors/photo_sensor.py
flowchem/components/sensors/pressure_sensor.py
flowchem/components/sensors/sensor.py
flowchem/components/technical/__init__.py
flowchem/components/technical/photo.py
flowchem/components/technical/power.py
flowchem/components/technical/pressure.py
flowchem/components/technical/temperature.py
flowchem/components/valves/__init__.py
flowchem/components/valves/distribution_valves.py
flowchem/components/valves/injection_valves.py
flowchem/components/valves/valve.py
flowchem/devices/__init__.py
flowchem/devices/flowchem_device.py
flowchem/devices/known_plugins.py
flowchem/devices/list_known_device_type.py
flowchem/devices/bronkhorst/__init__.py
flowchem/devices/bronkhorst/el_flow.py
flowchem/devices/bronkhorst/el_flow_component.py
flowchem/devices/custom/__init__.py
flowchem/devices/custom/peltier_cooler.py
flowchem/devices/custom/peltier_cooler_component.py
flowchem/devices/dataapex/__init__.py
flowchem/devices/dataapex/clarity.py
flowchem/devices/dataapex/clarity_hplc_control.py
flowchem/devices/hamilton/__init__.py
flowchem/devices/hamilton/ml600.py
flowchem/devices/hamilton/ml600_finder.py
flowchem/devices/hamilton/ml600_pump.py
flowchem/devices/hamilton/ml600_valve.py
flowchem-1.1.0.post1.dist-info/licenses/LICENSE
flowchem-1.1.0.post1.dist-info/METADATA
flowchem-1.1.0.post1.dist-info/WHEEL
flowchem-1.1.0.post1.dist-info/entry_points.txt
flowchem-1.1.0.post1.dist-info/top_level.txt
flowchem-1.1.0.post1.dist-info/RECORD
